{
    "Ar36": {
        "error": 0.0003864643274134202,
        "error_type": "SEM",
        "filter_outliers_dict": {
            "filter_outliers": true,
            "iterations": 1,
            "std_devs": 2,
            "use_iqr_filtering": false,
            "use_standard_deviation_filtering": true
        },
        "fit": "Parabolic",
        "fn": 600,
        "include_baseline_error": false,
        "n": 600,
        "outlier_excluded": [],
        "reviewed": true,
        "user_excluded": [],
        "value": 0.022079590879946084
    },
    "Ar37": {
        "error": 0.0038901400351789533,
        "error_type": "SEM",
        "filter_outliers_dict": {
            "filter_outliers": true,
            "iterations": 1,
            "std_devs": 2,
            "use_iqr_filtering": false,
            "use_standard_deviation_filtering": true
        },
        "fit": "Linear",
        "fn": 582,
        "include_baseline_error": false,
        "n": 600,
        "outlier_excluded": [
            439,
            2,
            356,
            357,
            421,
            167,
            104,
            41,
            440,
            521,
            77,
            590,
            239,
            16,
            145,
            87,
            24,
            508
        ],
        "reviewed": true,
        "user_excluded": [],
        "value": 0.3438835295480286
    },
    "Ar38": {
        "error": 0.010381799796900668,
        "error_type": "SEM",
        "filter_outliers_dict": {
            "filter_outliers": true,
            "iterations": 1,
            "std_devs": 2,
            "use_iqr_filtering": false,
            "use_standard_deviation_filtering": true
        },
        "fit": "Linear",
        "fn": 600,
        "include_baseline_error": false,
        "n": 600,
        "outlier_excluded": [],
        "reviewed": true,
        "user_excluded": [],
        "value": 6.271999174980625
    },
    "Ar39": {
        "error": 0.02876914112322345,
        "error_type": "SEM",
        "filter_outliers_dict": {
            "filter_outliers": true,
            "iterations": 1,
            "std_devs": 2,
            "use_iqr_filtering": false,
            "use_standard_deviation_filtering": true
        },
        "fit": "Parabolic",
        "fn": 600,
        "include_baseline_error": false,
        "n": 600,
        "outlier_excluded": [],
        "reviewed": true,
        "user_excluded": [],
        "value": 525.0353292942586
    },
    "Ar40": {
        "error": 0.05824522390680142,
        "error_type": "SEM",
        "filter_outliers_dict": {
            "filter_outliers": true,
            "iterations": 1,
            "std_devs": 2,
            "use_iqr_filtering": false,
            "use_standard_deviation_filtering": true
        },
        "fit": "Parabolic",
        "fn": 600,
        "include_baseline_error": false,
        "n": 600,
        "outlier_excluded": [],
        "reviewed": true,
        "user_excluded": [],
        "value": 1543.6646528367844
    },
    "Ar41": {
        "error": 0.008992278353661147,
        "error_type": "SEM",
        "filter_outliers_dict": {
            "filter_outliers": true,
            "iterations": 1,
            "std_devs": 2
        },
        "fit": "Linear",
        "value": -0.04320537110693784
    }
}